s3filefields/__init__.py
s3filefields/fields.py
django_s3copyfield-0.0.0a1.dist-info/LICENSE
django_s3copyfield-0.0.0a1.dist-info/METADATA
django_s3copyfield-0.0.0a1.dist-info/WHEEL
django_s3copyfield-0.0.0a1.dist-info/top_level.txt
django_s3copyfield-0.0.0a1.dist-info/RECORD
