Metadata-Version: 2.1
Name: django-s3copyfield
Version: 0.0.0a1
Summary: UNKNOWN
Home-page: https://github.com/davidslusser/django-s3filefield
Author: David Slusser
Author-email: dbslusser@gmail.com
License: MIT
Platform: any
Requires-Python: >=3.8
License-File: LICENSE
Requires-Dist: boto3
Requires-Dist: Django
Requires-Dist: django-storages
